{
  "schema_version": "1.11.0",
  "generated_at": "2026-07-22T20:47:22Z",
  "current_slice": "Feature 072 public query gateway v1",
  "functional_head": "856a6edee20cdb14a16a89d0d1a831faadbf166e",
  "summary": {
    "resolved_feature_findings": 8,
    "critical_or_high_open_in_feature": 0,
    "global_blockers_remain": true
  },
  "feature_findings": [
    {
      "id": "PQG-CRIT-001",
      "severity": "critical",
      "status": "resolved",
      "finding": "Browser query boundary was absent.",
      "resolution": "Implemented POST /api/public/v1/query, disabled by default and ahead of the legacy production gate."
    },
    {
      "id": "PQG-CRIT-002",
      "severity": "critical",
      "status": "resolved",
      "finding": "Browser could supply tenant or service identity.",
      "resolution": "Closed request excludes tenant/credential; Authorization and Cookie are rejected; tenant/jurisdiction are server-bound."
    },
    {
      "id": "PQG-CRIT-003",
      "severity": "critical",
      "status": "resolved",
      "finding": "Public retrieval could expose foreign/private evidence.",
      "resolution": "Forced-RLS tenant transaction and strict public/active/processed/accepted/clean eligibility passed PostgreSQL gates."
    },
    {
      "id": "PQG-HIGH-004",
      "severity": "high",
      "status": "resolved",
      "finding": "Anonymous abuse could bypass retrieval controls.",
      "resolution": "Global and HMAC per-client database buckets run before body parsing/retrieval; edge controls remain required."
    },
    {
      "id": "PQG-HIGH-005",
      "severity": "high",
      "status": "resolved",
      "finding": "Comparative evidence could be presented as official answer.",
      "resolution": "Comparative/validation-required candidates remain citations or limitations and never produce supported answer content."
    },
    {
      "id": "PQG-HIGH-006",
      "severity": "high",
      "status": "resolved",
      "finding": "Audit could retain query or network identity.",
      "resolution": "Audit allowlist excludes query, excerpts, URLs, IP and user-agent; rate identity persists only a 32-byte HMAC digest."
    },
    {
      "id": "PQG-HIGH-007",
      "severity": "high",
      "status": "resolved",
      "finding": "Source links could leak credentials or signatures.",
      "resolution": "Public citations require HTTPS URLs with no userinfo, query or fragment."
    },
    {
      "id": "PQG-HIGH-008",
      "severity": "high",
      "status": "resolved",
      "finding": "Feature implementation could be mistaken for deployment.",
      "resolution": "Gateway remains disabled by default; no Pages API URL, cloud resource, merge or deployment is claimed."
    }
  ],
  "open_findings": [
    {
      "id": "PQG-OPEN-ENABLEMENT-001",
      "severity": "critical",
      "status": "open",
      "area": "public_gateway_enablement",
      "finding": "Gateway is implemented but cannot be enabled until an authorized ingested public corpus, edge controls, staging and deployment approval exist."
    },
    {
      "id": "PROG-CORPUS-001",
      "severity": "critical",
      "status": "open",
      "area": "corpus",
      "finding": "No authorized durable corpus bytes or real ingestion exist."
    },
    {
      "id": "E2E-OPEN-RUNNER-001",
      "severity": "high",
      "status": "open",
      "area": "staging_execution",
      "finding": "No runner has executed the staging lifecycle and twenty API/system journeys."
    },
    {
      "id": "E2E-OPEN-IDP-002",
      "severity": "critical",
      "status": "open",
      "area": "human_identity",
      "finding": "No approved IdP/BFF/session or authenticated role-aware UI exists."
    },
    {
      "id": "E2E-OPEN-CONSUMERS-003",
      "severity": "high",
      "status": "open",
      "area": "external_integrations",
      "finding": "OS Electoral and Content Agency have not executed consumer suites."
    },
    {
      "id": "PROG-OPS-001",
      "severity": "critical",
      "status": "open",
      "area": "operations",
      "finding": "GCP is architecture only; infrastructure, observability, load/HA, recovery, privacy, merge and deployment are absent."
    }
  ],
  "publication": {
    "branch": "feature/public-query-gateway-v1",
    "functional_sha": "856a6edee20cdb14a16a89d0d1a831faadbf166e",
    "remote_sha_verified": true,
    "ci_run_id": 29955124279,
    "ci_status": "success",
    "ci_conclusion": "success",
    "pr": null,
    "merged": false,
    "deployed": false
  }
}
